tbcms/__init__.py
tbcms/__main__.py
tbcms/py.typed
tbcms/server.py
tbcms/files/presents.json
tbcms/files/version.txt
tbcms-1.0.0.dist-info/LICENSE
tbcms-1.0.0.dist-info/METADATA
tbcms-1.0.0.dist-info/WHEEL
tbcms-1.0.0.dist-info/top_level.txt
tbcms-1.0.0.dist-info/RECORD
