Metadata-Version: 2.1
Name: tbcms
Version: 1.0.0
Home-page: https://github.com/fieryhenry/tbcms
Author: fieryhenry
Classifier: Programming Language :: Python :: 3
Classifier: License :: OSI Approved :: MIT License
Classifier: Operating System :: OS Independent
Requires-Python: >=3.9
License-File: LICENSE
Requires-Dist: Flask
Requires-Dist: Requests
